crispr_da/CRISPR_DeepEnsemble.py
crispr_da/__init__.py
crispr_da/analysis.py
crispr_da/cache.py
crispr_da/collection.py
crispr_da/config.py
crispr_da/data.py
crispr_da/dataset.py
crispr_da/guide.py
crispr_da/off_target.py
crispr_da/on_target.py
crispr_da/utils.py
crispr_da/visualise.py
crispr_da/ISSL/CMakeLists.txt
crispr_da/ISSL/ISSLCreateIndex.cpp
crispr_da/ISSL/ISSLGetOfftargets.cpp
crispr_da/ISSL/ISSLScoreOfftargets.cpp
crispr_da/ISSL/include/fmt/args.h
crispr_da/ISSL/include/fmt/chrono.h
crispr_da/ISSL/include/fmt/color.h
crispr_da/ISSL/include/fmt/compile.h
crispr_da/ISSL/include/fmt/core.h
crispr_da/ISSL/include/fmt/format-inl.h
crispr_da/ISSL/include/fmt/format.h
crispr_da/ISSL/include/fmt/os.h
crispr_da/ISSL/include/fmt/ostream.h
crispr_da/ISSL/include/fmt/printf.h
crispr_da/ISSL/include/fmt/ranges.h
crispr_da/ISSL/include/fmt/std.h
crispr_da/ISSL/include/fmt/xchar.h
crispr_da/ISSL/include/libpopcnt/libpopcnt.h
crispr_da/ISSL/include/phmap/btree.h
crispr_da/ISSL/include/phmap/conanfile.py
crispr_da/ISSL/include/phmap/meminfo.h
crispr_da/ISSL/include/phmap/phmap.h
crispr_da/ISSL/include/phmap/phmap_base.h
crispr_da/ISSL/include/phmap/phmap_bits.h
crispr_da/ISSL/include/phmap/phmap_config.h
crispr_da/ISSL/include/phmap/phmap_dump.h
crispr_da/ISSL/include/phmap/phmap_fwd_decl.h
crispr_da/ISSL/include/phmap/phmap_utils.h
crispr_da/ISSL/penalties/CMakeLists.txt
crispr_da/ISSL/penalties/penalties.cpp
crispr_da/ISSL/penalties/penalties.hpp
crispr_da/resources/CRISPR_DeepEnsemble.zip
crispr_da/resources/__init__.py
crispr_da/resources/human_viruses.csv
crispr_da/resources/model-1_0_2.txt
crispr_da/resources/slice-10-37.txt
crispr_da/resources/slice-4-5.txt
crispr_da/resources/slice-8-20.txt
crispr_da/resources/trainingResults.pkl
crispr_da/scripts/__init__.py
crispr_da/scripts/cli.py
crispr_da-1.0.0.dist-info/licenses/LICENCE
crispr_da-1.0.0.dist-info/METADATA
crispr_da-1.0.0.dist-info/WHEEL
crispr_da-1.0.0.dist-info/entry_points.txt
crispr_da-1.0.0.dist-info/top_level.txt
crispr_da-1.0.0.dist-info/RECORD
