Metadata-Version: 2.4
Name: crispr_da
Version: 1.0.0
Summary: Adapting CRISPR gRNA design for detection assays.
Author-email: "Carl Schmitz, Jake Bradford, Dimitri Perrin" <dimitri.perrin@qut.edu.au>
License-Expression: BSD-3-Clause
Project-URL: Homepage, https://biomedicaldatascience.com/index.html
Project-URL: Repository, https://github.com/bmds-lab/crispr-da.git
Project-URL: Issues, https://github.com/bmds-lab/crispr-da/issues
Classifier: Intended Audience :: Science/Research
Classifier: Programming Language :: Python :: 3
Classifier: Operating System :: OS Independent
Requires-Python: >=3.12
License-File: LICENCE
Requires-Dist: torch==2.3.1
Requires-Dist: biopython>=1.86
Requires-Dist: pandas>=1.4.1
Requires-Dist: ete3>=3.1.3
Requires-Dist: requests>=2.32.5
Requires-Dist: dill
Requires-Dist: matplotlib
Requires-Dist: tqdm
Dynamic: license-file
